strprofiler/__init__.py
strprofiler/clastr.py
strprofiler/cli.py
strprofiler/shiny_app/__init__.py
strprofiler/shiny_app/calc_functions.py
strprofiler/shiny_app/clastr_api.py
strprofiler/shiny_app/shiny_app.py
strprofiler/shiny_app/www/Example_Batch_File.csv
strprofiler/shiny_app/www/Example_Custom_Database.csv
strprofiler/shiny_app/www/favicon.ico
strprofiler/shiny_app/www/help.html
strprofiler/shiny_app/www/help.md
strprofiler/shiny_app/www/logo.png
strprofiler/shiny_app/www/logo.svg
strprofiler/shiny_app/www/main_database.csv
strprofiler/shiny_app/www/masters_query.png
strprofiler/shiny_app/www/masters_query_inverted.png
strprofiler/shiny_app/www/masters_ref.png
strprofiler/shiny_app/www/masters_ref_inverted.png
strprofiler/shiny_app/www/tanabe.png
strprofiler/shiny_app/www/tanabe_inverted.png
strprofiler/strprofiler.py
strprofiler/utils.py
strprofiler-0.4.2.dist-info/LICENSE
strprofiler-0.4.2.dist-info/METADATA
strprofiler-0.4.2.dist-info/WHEEL
strprofiler-0.4.2.dist-info/entry_points.txt
strprofiler-0.4.2.dist-info/RECORD
