Metadata-Version: 2.1
Name: strprofiler
Version: 0.4.2
Summary: A python package, CLI tool, and Shiny application to compare short tandem repeat (STR) profiles.
Home-page: https://github.com/j-andrews7/strprofiler
License: MIT
Author: Jared Andrews
Author-email: jared.andrews07@gmail.com
Requires-Python: >=3.9,<4.0
Classifier: License :: OSI Approved :: MIT License
Classifier: Programming Language :: Python :: 3
Classifier: Programming Language :: Python :: 3.9
Classifier: Programming Language :: Python :: 3.10
Classifier: Programming Language :: Python :: 3.11
Classifier: Programming Language :: Python :: 3.12
Requires-Dist: Jinja2 (>=3.1.3,<4.0.0)
Requires-Dist: faicons (>=0.2.2,<0.3.0)
Requires-Dist: flatten-json (>=0.1.14,<0.2.0)
Requires-Dist: numpy (>=1.26.3,<2.0.0)
Requires-Dist: openpyxl (>=3.0.10,<4.0.0)
Requires-Dist: pandas (>=2.2,<3.0)
Requires-Dist: requests (>=2.31.0,<3.0.0)
Requires-Dist: rich-click (>=1.5.2,<2.0.0)
Requires-Dist: shiny (>=0.9.0,<0.10.0)
Requires-Dist: shinyswatch (>=0.4.2,<0.5.0)
Project-URL: Documentation, https://strprofiler.readthedocs.io/en/latest/
Project-URL: Paper, https://doi.org/10.1093/bioinformatics/btae713
Project-URL: Repository, https://github.com/j-andrews7/strprofiler
